textllm.py
textllm-20250201.0.1.dist-info/METADATA
textllm-20250201.0.1.dist-info/WHEEL
textllm-20250201.0.1.dist-info/entry_points.txt
textllm-20250201.0.1.dist-info/top_level.txt
textllm-20250201.0.1.dist-info/RECORD
