Metadata-Version: 2.1
Name: textllm
Version: 20250201.0.1
Summary: Simple text file based interface to LLMs
Author: Justin Winokur
Author-email: Jwink3101@users.noreply.github.com
Classifier: Programming Language :: Python :: 3
Classifier: License :: OSI Approved :: MIT License
Classifier: Operating System :: OS Independent
Requires-Python: >=3.8
Requires-Dist: python-dotenv
Requires-Dist: langchain
